vpnua/__init__.py
vpnua/basedefs.py
vpnua/config.py
vpnua/ldapdata.py
vpnua/limesdata.py
vpnua/redisdata.py
vpnua/special_rules.py
vpnua/utils.py
vpnua_jyrgenn-2023.1129.1201.dist-info/METADATA
vpnua_jyrgenn-2023.1129.1201.dist-info/WHEEL
vpnua_jyrgenn-2023.1129.1201.dist-info/top_level.txt
vpnua_jyrgenn-2023.1129.1201.dist-info/RECORD
